LICENSE
gr_common/__init__.py
gr_common/data/__init__.py
gr_common/data/aerospike_client.py
gr_common/data/interfaces.py
gr_common/exceptions/__init__.py
gr_common/exceptions/base_exception.py
gr_common/exceptions/base_http_exception.py
gr_common/exceptions/data_exceptions.py
gr_common/exceptions/http_exceptions.py
gr_common/schemas/__init__.py
gr_common/schemas/base_schemas.py
gr_common/settings/__init__.py
gr_common/settings/aerospike.py
gr_common/settings/oracle.py
gr_common/utils/__init__.py
gr_common/utils/serialize.py
gr_common-0.1.0.dist-info/LICENSE
gr_common-0.1.0.dist-info/WHEEL
gr_common-0.1.0.dist-info/METADATA
gr_common-0.1.0.dist-info/RECORD
