Metadata-Version: 2.1
Name: gr-common
Version: 0.1.0
Summary: Golden Record common library
Home-page: https://gitlab.services.mts.ru/gr/develop/gr_common
License: MIT
Author: Nikita Veselenko
Author-email: nyveselen1@mts.ru
Requires-Python: >=3.10,<4.0
Classifier: License :: OSI Approved :: MIT License
Classifier: Operating System :: OS Independent
Classifier: Programming Language :: Python :: 3
Classifier: Programming Language :: Python :: 3.10
Classifier: Programming Language :: Python :: 3.11
Classifier: Programming Language :: Python :: 3.10
Requires-Dist: aerospike (>=8.0.0,<9.0.0)
Requires-Dist: pydantic (>=1.10.2,<2.0.0)
Project-URL: Repository, https://gitlab.services.mts.ru/gr/develop/gr_common
